Hardware_Slow/MicroBlaze/MicroBlaze.srcs/sources_1/new/CRC32.v
// Top level module SHA-256 and AXI interfaces
module sha_256 #(
    parameter integer AXI_ADDR_WIDTH = 32,
    parameter integer AXI_DATA_WIDTH = 32,
    parameter READ_ADDR = 32'hC000_0000,
    parameter WRITE_ADDR = 32'hC000_0100
)(
    input  wire [2:0] GPIO_start,
    output reg        GPIO_complete,
    input  wire       M_AXI_ACLK,
    input  wire       M_AXI_ARESETN,

    // AXI write interface
    output wire [AXI_DATA_WIDTH-1:0]     M_AXI_WDATA,
    output wire [AXI_DATA_WIDTH/8-1 : 0] M_AXI_WSTRB,
    output wire [31:0]                   M_AXI_AWADDR,
    output wire [2:0]  M_AXI_AWPROT,
    output wire        M_AXI_AWVALID,
    input  wire        M_AXI_AWREADY,
    output wire        M_AXI_WVALID,
    input  wire        M_AXI_WREADY,
    input  wire [1:0]  M_AXI_BRESP,
    input  wire        M_AXI_BVALID,
    output wire        M_AXI_BREADY,

    // AXI read interface
    output wire [31:0] M_AXI_ARADDR,
    output wire [2:0]  M_AXI_ARPROT,
    output wire        M_AXI_ARVALID,
    input  wire        M_AXI_ARREADY,
    input  wire [AXI_DATA_WIDTH-1:0] M_AXI_RDATA,
    input  wire [1:0]  M_AXI_RRESP,
    input  wire        M_AXI_RVALID,
    output wire        M_AXI_RREADY
);

    // State definitions
    localparam [4:0]
        IDLE          = 5'b00000,
        READ_BLOCK    = 5'b00001,
        WAIT_READ     = 5'b00010,
        STORE_WORD    = 5'b00011,
        START_HASH    = 5'b00100,
        WRITING       = 5'b00101,
        WAIT_WRITE    = 5'b00110,
        RESPONSE      = 5'b00111,
        NEXT_WORD     = 5'b01000,
        DONE          = 5'b01001;
        
    // Control MB signal definitions
    localparam [2:0]
        NO_OP      = 3'b000,
        START_HASH_SIGNAL = 3'b001,
        RESET_HASH_SIGNAL = 3'b010,
        LARGE_HASH_SIGNAL = 3'b011;

    // Internal registers
    reg [4:0] state;
    wire [255:0] hash_out;
    wire hash_done;
    reg hash_start;
    reg reset_hash; 
    reg large_hash;
    reg [255:0] final_hash;
    reg [3:0] word_counter;  
    reg [31:0] current_word;
    reg [511:0] message_block;
    reg axi_awvalid;
    reg axi_wvalid;
    reg axi_bready;
    reg axi_arvalid;
    reg axi_rready;
    reg [31:0] read_addr;
    reg [31:0] write_addr;

    // Fixed assignments
    assign M_AXI_AWADDR = write_addr;
    assign M_AXI_ARADDR = read_addr;
    assign M_AXI_AWVALID = axi_awvalid;
    assign M_AXI_WVALID = axi_wvalid;
    assign M_AXI_BREADY = axi_bready;
    assign M_AXI_ARVALID = axi_arvalid;
    assign M_AXI_RREADY = axi_rready;
    assign M_AXI_WSTRB = 4'b1111;
    assign M_AXI_AWPROT = 3'b000;
    assign M_AXI_ARPROT = 3'b000;
    assign M_AXI_WDATA = current_word;

    // SHA-256 instance
    sha256 sha256_inst (
        .clk(M_AXI_ACLK),
        .rst(~M_AXI_ARESETN),
        .reset_hash(reset_hash),
        .large_hash(large_hash),
        .start(hash_start),
        .message_block(message_block),
        .hash(hash_out),
        .done(hash_done)
    );

    // Main state machine
    always @(posedge M_AXI_ACLK) begin
        if (~M_AXI_ARESETN) begin
            state <= IDLE;
            reset_hash <= 1'b0;
            large_hash <= 1'b0;
            axi_awvalid <= 1'b0;
            axi_wvalid <= 1'b0;
            axi_bready <= 1'b0;
            axi_arvalid <= 1'b0;
            axi_rready <= 1'b0;
            GPIO_complete <= 1'b0;
            hash_start <= 1'b0;
            word_counter <= 4'b0000;
            read_addr <= READ_ADDR;
            write_addr <= WRITE_ADDR;
            message_block <= 512'b0;
            current_word <= 32'b0;
            final_hash <= 256'b0;
        end
        else begin
            case (state)
                IDLE: begin
                    case (GPIO_start)
                        START_HASH_SIGNAL: begin
                            reset_hash <= 1'b0;
                            large_hash <= 1'b0;
                            state <= READ_BLOCK;
                            word_counter <= 4'b0000;
                            read_addr <= READ_ADDR;
                            axi_arvalid <= 1'b1;
                            axi_rready <= 1'b1;
                            GPIO_complete <= 1'b0;
                        end
                
                        RESET_HASH_SIGNAL: begin
                            reset_hash <= 1'b1;
                            state <= IDLE;
                            axi_awvalid <= 1'b0;
                            axi_wvalid <= 1'b0;
                            axi_bready <= 1'b0;
                            axi_arvalid <= 1'b0;
                            axi_rready <= 1'b0;
                            GPIO_complete <= 1'b0;
                            hash_start <= 1'b0;
                            word_counter <= 4'b0000;
                            read_addr <= READ_ADDR;
                            write_addr <= WRITE_ADDR;
                            message_block <= 512'b0;
                            current_word <= 32'b0;
                            final_hash <= 256'b0;
                        end
                        
                        LARGE_HASH_SIGNAL: begin
                            large_hash <= 1'b1;
                            state <= IDLE;
                            axi_awvalid <= 1'b0;
                            axi_wvalid <= 1'b0;
                            axi_bready <= 1'b0;
                            axi_arvalid <= 1'b0;
                            axi_rready <= 1'b0;
                            GPIO_complete <= 1'b0;
                            hash_start <= 1'b0;
                            word_counter <= 4'b0000;
                            read_addr <= READ_ADDR;
                            write_addr <= WRITE_ADDR;
                            current_word <= 32'b0;
                        end
                
                        default: begin
                            reset_hash <= 1'b0;
                            state <= IDLE;
                            hash_start <= 1'b0;
                        end
                    endcase
                end

                READ_BLOCK: begin
                    if (M_AXI_ARREADY && axi_arvalid) begin
                        axi_arvalid <= 1'b0;
                        state <= WAIT_READ;
                    end
                end

                WAIT_READ: begin
                    if (M_AXI_RVALID && axi_rready) begin
                        state <= STORE_WORD;
                    end
                end

                STORE_WORD: begin
                    message_block[511-word_counter*32 -: 32] <= M_AXI_RDATA;
                    
                    if (word_counter == 4'b1111) begin
                        state <= START_HASH;
                        axi_rready <= 1'b0;
                    end else begin
                        word_counter <= word_counter + 1;
                        read_addr <= read_addr + 4;
                        axi_arvalid <= 1'b1;
                        state <= READ_BLOCK;
                    end
                end

                START_HASH: begin
                    hash_start <= 1'b1;
                    state <= WRITING;
                    word_counter <= 3'b000;
                    write_addr <= WRITE_ADDR;
                end

                WRITING: begin
                    hash_start <= 1'b0;
                    
                    if (hash_done) begin
                        final_hash <= hash_out;
                        case (word_counter)
                            3'b000: current_word <= hash_out[255:224];
                            3'b001: current_word <= hash_out[223:192];
                            3'b010: current_word <= hash_out[191:160];
                            3'b011: current_word <= hash_out[159:128];
                            3'b100: current_word <= hash_out[127:96];
                            3'b101: current_word <= hash_out[95:64];
                            3'b110: current_word <= hash_out[63:32];
                            3'b111: current_word <= hash_out[31:0];
                        endcase
                        axi_awvalid <= 1'b1;
                        axi_wvalid <= 1'b1;
                        axi_bready <= 1'b1;  
                        state <= WAIT_WRITE;
                    end
                end
                
                WAIT_WRITE: begin
                    if (M_AXI_AWREADY && M_AXI_AWVALID) begin
                        axi_awvalid <= 1'b0;
                    end 
                    if (M_AXI_WREADY && M_AXI_WVALID) begin
                        axi_wvalid <= 1'b0;
                        state <= RESPONSE;
                        // Don't deassert axi_bready here anymore
                    end
                end
                
                RESPONSE: begin
                    if (M_AXI_BVALID && M_AXI_BREADY) begin
                        axi_bready <= 1'b0;  
                        if (word_counter == 3'b111) begin
                            state <= DONE;
                            GPIO_complete <= 1'b1;
                        end else begin
                            state <= NEXT_WORD;
                        end
                    end
                end

                NEXT_WORD: begin
                    word_counter <= word_counter + 1;
                    write_addr <= write_addr + 4;
                    state <= WRITING;
                end

                DONE: begin
                    axi_awvalid <= 1'b0;
                    axi_wvalid <= 1'b0;
                    axi_bready <= 1'b0;
                    GPIO_complete <= 1'b1;
                    hash_start <= 1'b0;
                    if(GPIO_start == RESET_HASH_SIGNAL) 
                        state <= IDLE;
                    if(GPIO_start == LARGE_HASH_SIGNAL) 
                        state <= IDLE;
                end

                default: state <= IDLE;
            endcase
        end
    end

endmodule

// SHA-256 module with reset modification
module sha256 (
    input wire clk,
    input wire rst,
    input wire reset_hash,
    input wire large_hash,
    input wire start,
    input wire [511:0] message_block,
    output reg [255:0] hash,
    output reg done
);

    // State definitions
    localparam IDLE = 2'b00;
    localparam PROCESS = 2'b01;
    localparam FINISH = 2'b10;

    reg [1:0] state;
    reg [5:0] round_count;
    
    // Hash registers
    reg [31:0] H0, H1, H2, H3, H4, H5, H6, H7;
    reg [31:0] a, b, c, d, e, f, g, h;
    reg [31:0] T1, T2;
    wire [31:0] ch, maj, s0, s1;

    // Message schedule array
    reg [31:0] W [0:63];
    
    // K constants array
    reg [31:0] K [0:63];
    initial begin
        K[0] = 32'h428a2f98; K[1] = 32'h71374491; K[2] = 32'hb5c0fbcf; K[3] = 32'he9b5dba5;
        K[4] = 32'h3956c25b; K[5] = 32'h59f111f1; K[6] = 32'h923f82a4; K[7] = 32'hab1c5ed5;
        K[8] = 32'hd807aa98; K[9] = 32'h12835b01; K[10] = 32'h243185be; K[11] = 32'h550c7dc3;
        K[12] = 32'h72be5d74; K[13] = 32'h80deb1fe; K[14] = 32'h9bdc06a7; K[15] = 32'hc19bf174;
        K[16] = 32'he49b69c1; K[17] = 32'hefbe4786; K[18] = 32'h0fc19dc6; K[19] = 32'h240ca1cc;
        K[20] = 32'h2de92c6f; K[21] = 32'h4a7484aa; K[22] = 32'h5cb0a9dc; K[23] = 32'h76f988da;
        K[24] = 32'h983e5152; K[25] = 32'ha831c66d; K[26] = 32'hb00327c8; K[27] = 32'hbf597fc7;
        K[28] = 32'hc6e00bf3; K[29] = 32'hd5a79147; K[30] = 32'h06ca6351; K[31] = 32'h14292967;
        K[32] = 32'h27b70a85; K[33] = 32'h2e1b2138; K[34] = 32'h4d2c6dfc; K[35] = 32'h53380d13;
        K[36] = 32'h650a7354; K[37] = 32'h766a0abb; K[38] = 32'h81c2c92e; K[39] = 32'h92722c85;
        K[40] = 32'ha2bfe8a1; K[41] = 32'ha81a664b; K[42] = 32'hc24b8b70; K[43] = 32'hc76c51a3;
        K[44] = 32'hd192e819; K[45] = 32'hd6990624; K[46] = 32'hf40e3585; K[47] = 32'h106aa070;
        K[48] = 32'h19a4c116; K[49] = 32'h1e376c08; K[50] = 32'h2748774c; K[51] = 32'h34b0bcb5;
        K[52] = 32'h391c0cb3; K[53] = 32'h4ed8aa4a; K[54] = 32'h5b9cca4f; K[55] = 32'h682e6ff3;
        K[56] = 32'h748f82ee; K[57] = 32'h78a5636f; K[58] = 32'h84c87814; K[59] = 32'h8cc70208;
        K[60] = 32'h90befffa; K[61] = 32'ha4506ceb; K[62] = 32'hbef9a3f7; K[63] = 32'hc67178f2;
    end

    // SHA-256 functions
    assign ch = (e & f) ^ (~e & g);
    assign maj = (a & b) ^ (a & c) ^ (b & c);
    assign s0 = {a[1:0],a[31:2]} ^ {a[12:0],a[31:13]} ^ {a[21:0],a[31:22]};
    assign s1 = {e[5:0],e[31:6]} ^ {e[10:0],e[31:11]} ^ {e[24:0],e[31:25]};

    // Message schedule functions
    wire [31:0] sigma0, sigma1;
    assign sigma0 = {W[round_count-15][6:0],W[round_count-15][31:7]} ^ 
                    {W[round_count-15][17:0],W[round_count-15][31:18]} ^ 
                    (W[round_count-15] >> 3);
    
    assign sigma1 = {W[round_count-2][16:0],W[round_count-2][31:17]} ^ 
                    {W[round_count-2][18:0],W[round_count-2][31:19]} ^ 
                    (W[round_count-2] >> 10);

    // Next W value calculation
    wire [31:0] w_next = (round_count < 16) ? W[round_count] :
                         W[round_count-16] + sigma0 + W[round_count-7] + sigma1;

    // T1 and T2 calculation
    wire [31:0] t1_next = h + s1 + ch + K[round_count] + w_next;
    wire [31:0] t2_next = s0 + maj;

    always @(posedge clk or posedge rst) begin
        if(large_hash) begin
            state <= IDLE;
            round_count <= 0;
            done <= 0;
            // Initialize working variables
            a <= H0;
            b <= H1;
            c <= H2;
            d <= H3;
            e <= H4;
            f <= H5;
            g <= H6;
            h <= H7;
        end
        
        if (rst || reset_hash) begin
            state <= IDLE;
            round_count <= 0;
            done <= 0;
            
            // Initialize hash values
            H0 <= 32'h6a09e667;
            H1 <= 32'hbb67ae85;
            H2 <= 32'h3c6ef372;
            H3 <= 32'ha54ff53a;
            H4 <= 32'h510e527f;
            H5 <= 32'h9b05688c;
            H6 <= 32'h1f83d9ab;
            H7 <= 32'h5be0cd19;

            // Initialize working variables
            a <= 32'h6a09e667;
            b <= 32'hbb67ae85;
            c <= 32'h3c6ef372;
            d <= 32'ha54ff53a;
            e <= 32'h510e527f;
            f <= 32'h9b05688c;
            g <= 32'h1f83d9ab;
            h <= 32'h5be0cd19;

        end else begin
            case (state)
                IDLE: begin
                    if (start) begin
                        // Load message block into W
                        W[0] <= message_block[511:480];
                        W[1] <= message_block[479:448];
                        W[2] <= message_block[447:416];
                        W[3] <= message_block[415:384];
                        W[4] <= message_block[383:352];
                        W[5] <= message_block[351:320];
                        W[6] <= message_block[319:288];
                        W[7] <= message_block[287:256];
                        W[8] <= message_block[255:224];
                        W[9] <= message_block[223:192];
                        W[10] <= message_block[191:160];
                        W[11] <= message_block[159:128];
                        W[12] <= message_block[127:96];
                        W[13] <= message_block[95:64];
                        W[14] <= message_block[63:32];
                        W[15] <= message_block[31:0];
                        
                        // Reset working variables
                        a <= H0;
                        b <= H1;
                        c <= H2;
                        d <= H3;
                        e <= H4;
                        f <= H5;
                        g <= H6;
                        h <= H7;
                        
                        state <= PROCESS;
                        round_count <= 0;
                        done <= 0;
                    end
                end 

                PROCESS: begin
                    // Update message schedule
                    if (round_count >= 16) begin
                        W[round_count] <= w_next;
                    end

                    // Store T1 and T2
                    T1 <= t1_next;
                    T2 <= t2_next;

                    // Update working variables
                    h <= g;
                    g <= f;
                    f <= e;
                    e <= d + t1_next;
                    d <= c;
                    c <= b;
                    b <= a;
                    a <= t1_next + t2_next;

                    if (round_count == 63)
                        state <= FINISH;
                    else
                        round_count <= round_count + 1;
                end

                FINISH: begin
                    // Update hash values
                    H0 <= H0 + a;
                    H1 <= H1 + b;
                    H2 <= H2 + c;
                    H3 <= H3 + d;
                    H4 <= H4 + e;
                    H5 <= H5 + f;
                    H6 <= H6 + g;
                    H7 <= H7 + h;
                    
                    // Output final hash
                    hash <= {H0 + a, H1 + b, H2 + c, H3 + d,
                            H4 + e, H5 + f, H6 + g, H7 + h};
                    done <= 1;
                    state <= IDLE;
                end
            endcase
        end
    end

endmodule

Hardware_Slow/MicroBlaze/MicroBlaze.srcs/sim_1/new/sim.v
`timescale 1ns/1ps

module sha256_tb;
    // Inputs
    reg clk;
    reg rst;
    reg reset_hash;
    reg large_hash;
    reg start;
    reg [511:0] message_block;

    // Outputs
    wire [255:0] hash;
    wire done;

    // Instantiate the SHA-256 module
    sha256 uut (
        .clk(clk),
        .rst(rst),
        .reset_hash(reset_hash),
        .large_hash(large_hash),
        .start(start),
        .message_block(message_block),
        .hash(hash),
        .done(done)
    );

    // Clock generation
    initial begin
        clk = 0;
        forever #5 clk = ~clk;
    end

    // Test vectors
    reg [511:0] test_message1 = 512'h546865206f6c6420726164696f20637261636b6c656420746f206c6966652c2077686973706572696e6720736563726574732066726f6d206120666f72676f74;
    reg [511:0] test_message2 = 512'h74656e206572612e8000000000000000000000000000000000000000000000000000000000000000000000000000000000000000000000000000000000000240;

    // Test procedure
    initial begin
        // Initialize signals
        rst = 1;
        reset_hash = 0;
        large_hash = 0;
        start = 0;
        message_block = 0;

        // Wait for 100ns
        #100;

        // Release reset
        rst = 0;
        #20;

        // Test Case 1: First message block
        $display("Test Case 1: Processing first message block");
        message_block = test_message1;
        start = 1;
        #10;
        start = 0;

        // Wait for completion
        @(posedge done);
        $display("Hash result 1: %h", hash);
        #20;

        // Test Case 2: Second message block
        $display("Test Case 2: Processing second message block");
        large_hash = 1;
        #10;
        large_hash = 0;
        message_block = test_message2;
        start = 1;
        #10;
        start = 0;

        // Wait for completion
        @(posedge done);
        $display("Final hash result: %h", hash);

        // Test Case 3: Reset hash test
        $display("Test Case 3: Testing reset_hash");
        reset_hash = 1;
        #10;
        reset_hash = 0;
        message_block = test_message1;
        start = 1;
        #10;
        start = 0;

        // Wait for completion
        @(posedge done);
        $display("Hash after reset: %h", hash);

        // Add delay before finishing simulation
        #100;
        $display("Simulation completed");
        $finish;
    end

    // Monitor changes
    initial begin
        $monitor("Time=%0t rst=%b start=%b done=%b state=%b", 
                 $time, rst, start, done, uut.state);
    end

    // Optional: Dump waveform file
    initial begin
        $dumpfile("sha256_tb.vcd");
        $dumpvars(0, sha256_tb);
    end

    // Timeout watchdog
    initial begin
        #10000; // Timeout after 10000 time units
        $display("Timeout: Simulation took too long");
        $finish;
    end

    // Check for completion of each round
    always @(posedge clk) begin
        if (uut.state == uut.PROCESS) begin
            $display("Round %0d completed", uut.round_count);
        end
    end

    // Verification tasks
    task verify_hash;
        input [255:0] expected_hash;
        begin
            if (hash === expected_hash)
                $display("Hash verification PASSED");
            else
                $display("Hash verification FAILED. Expected: %h, Got: %h", expected_hash, hash);
        end
    endtask

endmodule

Hardware_Slow/MicroBlaze/MicroBlaze.sim/sim_1/behav/xsim/sha256_tb.vcd
$date
   Fri Mar  7 16:27:05 2025
$end

$version
  2024.1.2
  $dumpfile ("sha256_tb.vcd") 
$end

$timescale
  1ps
$end

$scope module sha256_tb $end
$var reg 1 ! clk $end
$var reg 1 " rst $end
$var reg 1 # reset_hash $end
$var reg 1 $ large_hash $end
$var reg 1 % start $end
$var reg 512 & message_block [511:0] $end
$var wire 256 ' hash [255:0] $end
$var wire 1 ( done $end
$var reg 512 ) test_message1 [511:0] $end
$var reg 512 * test_message2 [511:0] $end
$scope module uut $end
$var wire 1 + clk $end
$var wire 1 , rst $end
$var wire 1 - reset_hash $end
$var wire 1 . large_hash $end
$var wire 1 / start $end
$var wire 512 0 message_block [511:0] $end
$var reg 256 1 hash [255:0] $end
$var reg 1 2 done $end
$var reg 2 3 state [1:0] $end
$var reg 6 4 round_count [5:0] $end
$var reg 32 5 H0 [31:0] $end
$var reg 32 6 H1 [31:0] $end
$var reg 32 7 H2 [31:0] $end
$var reg 32 8 H3 [31:0] $end
$var reg 32 9 H4 [31:0] $end
$var reg 32 : H5 [31:0] $end
$var reg 32 ; H6 [31:0] $end
$var reg 32 < H7 [31:0] $end
$var reg 32 = a [31:0] $end
$var reg 32 > b [31:0] $end
$var reg 32 ? c [31:0] $end
$var reg 32 @ d [31:0] $end
$var reg 32 A e [31:0] $end
$var reg 32 B f [31:0] $end
$var reg 32 C g [31:0] $end
$var reg 32 D h [31:0] $end
$var reg 32 E T1 [31:0] $end
$var reg 32 F T2 [31:0] $end
$var wire 32 G ch [31:0] $end
$var wire 32 H maj [31:0] $end
$var wire 32 I s0 [31:0] $end
$var wire 32 J s1 [31:0] $end
$var wire 32 K sigma0 [31:0] $end
$var wire 32 L sigma1 [31:0] $end
$var wire 32 M w_next [31:0] $end
$var wire 32 N t1_next [31:0] $end
$var wire 32 O t2_next [31:0] $end
$upscope $end
$upscope $end
$enddefinitions $end

#0
$dumpvars
0!
1"
0#
0$
0%
b0 &
bx '
0(
b1010100011010000110010100100000011011110110110001100100001000000111001001100001011001000110100101101111001000000110001101110010011000010110001101101011011011000110010101100100001000000111010001101111001000000110110001101001011001100110010100101100001000000111011101101000011010010111001101110000011001010111001001101001011011100110011100100000011100110110010101100011011100100110010101110100011100110010000001100110011100100110111101101101001000000110000100100000011001100110111101110010011001110110111101110100 )
b1110100011001010110111000100000011001010111001001100001001011101000000000000000000000000000000000000000000000000000000000000000000000000000000000000000000000000000000000000000000000000000000000000000000000000000000000000000000000000000000000000000000000000000000000000000000000000000000000000000000000000000000000000000000000000000000000000000000000000000000000000000000000000000000000000000000000000000000000000000000000000000000000000000000000000000000000000000000000000000000000000000000000000000001001000000 *
0+
1,
0-
0.
0/
b0 0
bx 1
02
b0 3
b0 4
b1101010000010011110011001100111 5
b10111011011001111010111010000101 6
b111100011011101111001101110010 7
b10100101010011111111010100111010 8
b1010001000011100101001001111111 9
b10011011000001010110100010001100 :
b11111100000111101100110101011 ;
b1011011111000001100110100011001 <
b1101010000010011110011001100111 =
b10111011011001111010111010000101 >
b111100011011101111001101110010 ?
b10100101010011111111010100111010 @
b1010001000011100101001001111111 A
b10011011000001010110100010001100 B
b11111100000111101100110101011 C
b1011011111000001100110100011001 D
bx E
bx F
b11111100001011100100110001100 G
b111010011011111110011001100111 H
b11001110001000001011010001111110 I
b110101100001110010011100101011 J
bx K
bx L
bx M
bx N
b1000100100001001101011100101 O
$end

#5000
1!
1+

#10000
0!
0+

#15000
1!
1+

#20000
0!
0+

#25000
1!
1+

#30000
0!
0+

#35000
1!
1+

#40000
0!
0+

#45000
1!
1+

#50000
0!
0+

#55000
1!
1+

#60000
0!
0+

#65000
1!
1+

#70000
0!
0+

#75000
1!
1+

#80000
0!
0+

#85000
1!
1+

#90000
0!
0+

#95000
1!
1+

#100000
0!
0"
0+
0,

#105000
1!
1+

#110000
0!
0+

#115000
1!
1+

#120000
0!
1%
b1010100011010000110010100100000011011110110110001100100001000000111001001100001011001000110100101101111001000000110001101110010011000010110001101101011011011000110010101100100001000000111010001101111001000000110110001101001011001100110010100101100001000000111011101101000011010010111001101110000011001010111001001101001011011100110011100100000011100110110010101100011011100100110010101110100011100110010000001100110011100100110111101101101001000000110000100100000011001100110111101110010011001110110111101110100 &
0+
1/
b1010100011010000110010100100000011011110110110001100100001000000111001001100001011001000110100101101111001000000110001101110010011000010110001101101011011011000110010101100100001000000111010001101111001000000110110001101001011001100110010100101100001000000111011101101000011010010111001101110000011001010111001001101001011011100110011100100000011100110110010101100011011100100110010101110100011100110010000001100110011100100110111101101101001000000110000100100000011001100110111101110010011001110110111101110100 0

#125000
1!
1+
b1 3
b1010100011010000110010100100000 M
b1000111111000000101001010001000 N

#130000
0!
0%
0+
0/

#135000
1!
1+
b1 4
b1010000011100001110110101101101 =
b1101010000010011110011001100111 >
b10111011011001111010111010000101 ?
b111100011011101111001101110010 @
b11101101001100000100011111000010 A
b1010001000011100101001001111111 B
b10011011000001010110100010001100 C
b11111100000111101100110101011 D
b1000111111000000101001010001000 E
b1000100100001001101011100101 F
b1010011000001010110101001001110 G
b1111010011000011110111001100101 H
b11111100110000110000110110011101 I
b1101011110010101000011001100001 J
b1101111011011000110010000100000 M
b10111110111101110111001100001011 N
b1110111001001001111110000000010 O

#140000
0!
0+

#145000
1!
1+
b10 4
b110110000111000110111100001101 =
b1010000011100001110110101101101 >
b1101010000010011110011001100111 ?
b10111011011001111010111010000101 @
b11111011011001100110011001111101 A
b11101101001100000100011111000010 B
b1010001000011100101001001111111 C
b10011011000001010110100010001100 D
b10111110111101110111001100001011 E
b1110111001001001111110000000010 F
b11101001001010000101011001000010 G
b1110010000110001110111101101101 H
b1000100010100101001111111111000 I
b10001011011000011100101110101000 J
b111110001000010011101010100000 L
b1110010011000010110010001101001 M
b110111101100011110101010101110 N
b10110110011010111000111101100101 O

#150000
0!
0+

#155000
1!
1+
b11 4
b11101110000111010111101000010011 =
b110110000111000110111100001101 >
b1010000011100001110110101101101 ?
b1101010000010011110011001100111 @
b11110011000110011001100100110011 A
b11111011011001100110011001111101 B
b11101101001100000100011111000010 C
b1010001000011100101001001111111 D
b110111101100011110101010101110 E
b10110110011010111000111101100101 F
b11111111001000000100011011110001 G
b1110110000111000110111100001101 H
b1011110111100000110000111010111 I
b1100101011111101001110010101110 J
b10111110100011111110000101000010 L
b1101111001000000110001101110010 M
b1110100000110111010100110101 N
b11010101000011001101000011100100 O

#160000
0!
0+

#165000
1!
1+
b100 4
b11100011100100000100011000011001 =
b11101110000111010111101000010011 >
b110110000111000110111100001101 ?
b1010000011100001110110101101101 @
b1111000100011010101101110011100 A
b11110011000110011001100100110011 B
b11111011011001100110011001111101 C
b11101101001100000100011111000010 D
b1110100000110111010100110101 E
b11010101000011001101000011100100 F
b11110011011010110011110101110001 G
b11100110000111000110111000011001 H
b1001001100110110101010001010 I
b1000100110000001110101011111001 J
b10011110101001010000111100100101 L
b1100001011000110110101101101100 M
b11000000000101101001110111110011 N
b11101111010011111101100010100011 O

#170000
0!
0+

#175000
1!
1+
b101 4
b10101111011001100111011010010110 =
b11100011100100000100011000011001 >
b11101110000111010111101000010011 ?
b110110000111000110111100001101 @
b10000100001111000101101100000 A
b1111000100011010101101110011100 B
b11110011000110011001100100110011 C
b11111011011001100110011001111101 D
b11000000000101101001110111110011 E
b11101111010011111101100010100011 F
b11110011100111010001101100010011 G
b11101111000101000111011000010011 H
b10000110101101101011110000101011 I
b10101111100001011011111011010100 J
b111101110011001011001001101100 L
b1100101011001000010000001110100 M
b1011101110111100111001011001001 N
b1110101110010110011001000111110 O

#180000
0!
0+

#185000
1!
1+
b110 4
b11010011101010011010010100000111 =
b10101111011001100111011010010110 >
b11100011100100000100011000011001 ?
b11101110000111010111101000010011 @
b10010011111110101110000111010110 A
b10000100001111000101101100000 B
b1111000100011010101101110011100 C
b11110011000110011001100100110011 D
b1011101110111100111001011001001 E
b1110101110010110011001000111110 F
b1111000100001111001101101001000 G
b11100011101000000110011000010111 H
b1111010010000001110101101000010 I
b10011101111011010111111110010010 J
b11011000110000111110010001000111 L
b1101111001000000110110001101001 M
b1010111011101010001100011010 N
b1011101111000010101000101011001 O

#190000
0!
0+

#195000
1!
1+
b111 4
b1101000110011111111010001110011 =
b11010011101010011010010100000111 >
b10101111011001100111011010010110 ?
b11100011100100000100011000011001 @
b11111001000011000001110100101101 A
b10010011111110101110000111010110 B
b10000100001111000101101100000 C
b1111000100011010101101110011100 D
b1010111011101010001100011010 E
b1011101111000010101000101011001 F
b10010001100010111000001101000100 G
b11101011111011111111010000010111 H
b1000110011110010111011011000000 I
b10010100010101011000011100001011 J
b10010100001011011110011100010110 L
b1100110011001010010110000100000 M
b10101111111011111111000011100000 N
b110010011010010110101011010111 O

#200000
0!
0+

#205000
1!
1+
b1000 4
b11100010010110010101101110110111 =
b1101000110011111111010001110011 >
b11010011101010011010010100000111 ?
b10101111011001100111011010010110 @
b10010011100000000011011011111001 A
b11111001000011000001110100101101 B
b10010011111110101110000111010110 C
b10000100001111000101101100000 D
b10101111111011111111000011100000 E
b110010011010010110101011010111 F
b10010001011110101101010100101111 G
b11100010110010011111010100110111 H
b1000000010001111001101110101110 I
b11111001011001110000110000010100 J
b111011101000100101001001101111 L
b1110111011010000110100101110011 M
b11101010110110011000000010101110 N
b100011000100011001000011100101 O

#210000
0!
0+

#215000
1!
1+
b1001 4
b1101111010110001000110010011 =
b11100010010110010101101110110111 >
b1101000110011111111010001110011 ?
b11010011101010011010010100000111 @
b10011010001111111111011101000100 A
b10010011100000000011011011111001 B
b11111001000011000001110100101101 C
b10010011111110101110000111010110 D
b11101010110110011000000010101110 E
b100011000100011001000011100101 F
b11110011000000000011111001101001 G
b1101000110010110101000110110011 H
b11100011101001001110011100001011 I
b11100101000000000001101001101110 J
b110011100011011010011010110101 L
b1110000011001010111001001101001 M
b11101110111001000000100000010111 N
b1001100011100000011100010111110 O

#220000
0!
0+

#225000
1!
1+
b1010 4
b111011010101000100000011010101 =
b1101111010110001000110010011 >
b11100010010110010101101110110111 ?
b1101000110011111111010001110011 @
b11000010100011011010110100011110 A
b10011010001111111111011101000100 B
b10010011100000000011011011111001 C
b11111001000011000001110100101101 D
b11101110111001000000100000010111 E
b1001100011100000011100010111110 F
b10010011000011011011011111100101 G
b101011010110010101000110010111 H
b11001011111111001111001111010 I
b10011110000001001110100001100000 J
b111001100010100000111101000011 L
b1101110011001110010000001110011 M
b10111100101101110110001110100011 N
b1000100110110001111000000010001 O

#230000
0!
0+

#235000
1!
1+
b1011 4
b1100100000101001110110100 =
b111011010101000100000011010101 >
b1101111010110001000110010011 ?
b11100010010110010101101110110111 @
b100101100001110101100000010110 A
b11000010100011011010110100011110 B
b10011010001111111111011101000100 C
b10010011100000000011011011111001 D
b10111100101101110110001110100011 E
b1000100110110001111000000010001 F
b10011010101111011010111101010110 G
b1001110100000101000110010101 H
b11011100100010101100100001101001 I
b10011001111111101010011010011001 J
b10111011001011000111101100010 L
b1100101011000110111001001100101 M
b10000010101011000111110100010000 N
b11100110010110110001100111111110 O

#240000
0!
0+

#245000
1!
1+
b1100 4
b1101001000001111001011100001110 =
b1100100000101001110110100 >
b111011010101000100000011010101 ?
b1101111010110001000110010011 @
b1100101000001011101100011000111 A
b100101100001110101100000010110 B
b11000010100011011010110100011110 C
b10011010001111111111011101000100 D
b10000010101011000111110100010000 E
b11100110010110110001100111111110 F
b10100111100011010111110100011110 G
b101001000101000101001110010100 H
b111100011011101001010001011011 I
b10000111100101001101010001101010 J
b1110100001011000100001100110111 L
b1110100011100110010000001100110 M
b10110000100100111100011010100110 N
b1100101100000101110011111101111 O

#250000
0!
0+

#255000
1!
1+
b1101 4
b10110000101101010111010010101 =
b1101001000001111001011100001110 >
b1100100000101001110110100 ?
b111011010101000100000011010101 @
b10111110011111101101100000111001 A
b1100101000001011101100011000111 B
b100101100001110101100000010110 C
b11000010100011011010110100011110 D
b10110000100100111100011010100110 E
b1100101100000101110011111101111 F
b100101100001011101100000000111 G
b1000101101001011110010100 H
b1101011100101110100111101001000 I
b11011110101000100010100001100100 J
b11010111011001110100011011000001 L
b1110010011011110110110100100000 M
b10111010000000111100110010100111 N
b1101100101011011110011011011100 O

#260000
0!
0+

#265000
1!
1+
b1110 4
b100110101100011011001110000011 =
b10110000101101010111010010101 >
b1101001000001111001011100001110 ?
b1100100000101001110110100 @
b11110101010110000000110101111100 A
b10111110011111101101100000111001 B
b1100101000001011101100011000111 C
b100101100001110101100000010110 D
b10111010000000111100110010100111 E
b1101100101011011110011011011100 F
b10110100010111011101100010111011 G
b100110000101111011011110000111 H
b10010011011110110101010111110111 I
b11110000010011010111010101001110 J
b11110100001000101110100001111111 L
b1100001001000000110011001101111 M
b11000111001011110001001100110101 N
b10111001100100110000110101111110 O

#270000
0!
0+

